LICENSE
README.md
setup.py
src/imgz/__init__.py
src/imgz/tabulation.py
src/imgz/transform.py
src/imgz/utils.py
src/imgz/xloss.py
src/imgz.egg-info/PKG-INFO
src/imgz.egg-info/SOURCES.txt
src/imgz.egg-info/dependency_links.txt
src/imgz.egg-info/top_level.txt