Metadata-Version: 2.1
Name: imgz
Version: 0.0.9
Summary: A image util package
Home-page: https://github.com/cvdnn/imgz
Author: cvdnn
Author-email: cvvdnn@gmail.com
License: UNKNOWN
Project-URL: Bug Tracker, https://github.com/cvdnn/imgz/issues
Keywords: pip,license,image,tool
Platform: UNKNOWN
Classifier: Programming Language :: Python :: 3
Classifier: License :: OSI Approved :: MIT License
Classifier: Operating System :: OS Independent
Requires-Python: >=3.6
License-File: LICENSE
